proxine/__init__.py
proxine/settings.py
proxine/sources.py
proxine-0.1.0.dist-info/METADATA
proxine-0.1.0.dist-info/WHEEL
proxine-0.1.0.dist-info/top_level.txt
proxine-0.1.0.dist-info/RECORD
